convml_data/.flake8
convml_data/__init__.py
convml_data/_version.py
convml_data/domain_picker_ui.py
convml_data/examples.py
convml_data/dataset/fetch_source_data.py
convml_data/dataset/generate.py
convml_data/dataset/stats.py
convml_data/pipeline/__init__.py
convml_data/pipeline/aux_sources.py
convml_data/pipeline/completion_summary.py
convml_data/pipeline/regridding.py
convml_data/pipeline/sampling.py
convml_data/pipeline/scene_sources.py
convml_data/pipeline/tiles.py
convml_data/pipeline/trajectory_tiles.py
convml_data/pipeline/triplets.py
convml_data/pipeline/utils.py
convml_data/sampling/__init__.py
convml_data/sampling/domain.py
convml_data/sampling/triplets.py
convml_data/sources/__init__.py
convml_data/sources/images.py
convml_data/sources/les.py
convml_data/sources/ceres/__init__.py
convml_data/sources/ceres/download.py
convml_data/sources/ceres/pipeline.py
convml_data/sources/ceres/query.py
convml_data/sources/goes16/__init__.py
convml_data/sources/goes16/pipeline.py
convml_data/sources/goes16/satpy_rgb.py
convml_data/sources/goes16/utils.py
convml_data/utils/domain_images.py
convml_data/utils/download.py
convml_data/utils/luigi.py
convml_data/utils/plot_domain.py
convml_data/utils/plot_scene.py
convml_data/utils/pytorch.py
convml_data/utils/time.py
convml_data/utils/time_filters.py
convml_data-0.2.1.dist-info/METADATA
convml_data-0.2.1.dist-info/WHEEL
convml_data-0.2.1.dist-info/top_level.txt
convml_data-0.2.1.dist-info/RECORD
